smart_image_cropper/__init__.py
smart_image_cropper/cropper.py
smart_image_cropper/exceptions.py
smart_image_cropper/utils.py
smart_image_cropper-1.2.0.dist-info/LICENSE
smart_image_cropper-1.2.0.dist-info/METADATA
smart_image_cropper-1.2.0.dist-info/WHEEL
smart_image_cropper-1.2.0.dist-info/top_level.txt
smart_image_cropper-1.2.0.dist-info/RECORD
