Metadata-Version: 2.1
Name: smart-image-cropper
Version: 1.2.0
Summary: An intelligent image cropping library that creates smart collages
Home-page: https://github.com/giumanuz/image_cropper
Author: Giulio Manuzzi
Author-email: Giulio Manuzzi <giuliomanuzzi@gmail.com>
Maintainer-email: Giulio Manuzzi <giuliomanuzzi@gmail.com>
License: MIT
Project-URL: Homepage, https://github.com/giumanuz/smart-image-cropper
Project-URL: Documentation, https://github.com/giumanuz/smart-image-cropper#readme
Project-URL: Repository, https://github.com/giumanuz/smart-image-cropper
Project-URL: Bug Tracker, https://github.com/giumanuz/smart-image-cropper/issues
Keywords: image processing,cropping,collage,computer vision,opencv
Classifier: Development Status :: 4 - Beta
Classifier: Intended Audience :: Developers
Classifier: License :: OSI Approved :: MIT License
Classifier: Operating System :: OS Independent
Classifier: Programming Language :: Python :: 3
Classifier: Programming Language :: Python :: 3.8
Classifier: Programming Language :: Python :: 3.9
Classifier: Programming Language :: Python :: 3.10
Classifier: Programming Language :: Python :: 3.11
Classifier: Programming Language :: Python :: 3.12
Classifier: Topic :: Multimedia :: Graphics
Classifier: Topic :: Scientific/Engineering :: Image Processing
Classifier: Topic :: Software Development :: Libraries :: Python Modules
Requires-Python: >=3.8
License-File: LICENSE
Requires-Dist: opencv-python>=4.5.0
Requires-Dist: numpy>=1.20.0
Requires-Dist: Pillow>=8.0.0
Requires-Dist: requests>=2.25.0
Provides-Extra: dev
Requires-Dist: pytest>=6.0; extra == "dev"
Requires-Dist: pytest-cov>=2.0; extra == "dev"
Requires-Dist: black>=21.0; extra == "dev"
Requires-Dist: flake8>=3.8; extra == "dev"
Requires-Dist: mypy>=0.812; extra == "dev"
